vipkid_common.py
vipkid_common-0.0.3.dist-info/DESCRIPTION.rst
vipkid_common-0.0.3.dist-info/METADATA
vipkid_common-0.0.3.dist-info/RECORD
vipkid_common-0.0.3.dist-info/WHEEL
vipkid_common-0.0.3.dist-info/metadata.json
vipkid_common-0.0.3.dist-info/top_level.txt
