Metadata-Version: 2.0
Name: vipkid-common
Version: 0.0.3
Summary: vipkid's common module
Home-page: http://www.zhaomingming.cn
Author: zhaomingming
Author-email: 13271929138@163.com
License: MIT
Platform: any
